griffe_fastapi/__init__.py
griffe_fastapi/_extension.py
griffe_fastapi/templates/material/_base/fastapi.html.jinja
griffe_fastapi/templates/material/fastapi.html.jinja
griffe_fastapi-0.1.5.dist-info/LICENSE
griffe_fastapi-0.1.5.dist-info/METADATA
griffe_fastapi-0.1.5.dist-info/WHEEL
griffe_fastapi-0.1.5.dist-info/entry_points.txt
griffe_fastapi-0.1.5.dist-info/RECORD
