Metadata-Version: 2.1
Name: griffe-fastapi
Version: 0.1.5
Summary: Griffe extension for FastAPI.
Keywords: griffe,griffe-extensions,fastapi
Author: fbraem
Author-email: franky.braem@gmail.com
Requires-Python: >=3.12,<4.0
Classifier: Programming Language :: Python :: 3
Classifier: Programming Language :: Python :: 3.12
Requires-Dist: griffe (>=1.5.1,<2.0.0)
